{
  "os":  "Windows-10-10.0.26100-SP0",
  "python":  "CPython 3.10.18",
  "startedAt":  "2025-10-21T13:12:24.068945Z",
  "program":  "c:\\Users\\victo\\OneDrive\\Escriptori\\3r\\Paradigms\\examples\\M3-2_Example_1 (DQN on Pong)\\M3-2_Example_1a (DQN on Pong, train).ipynb",
  "codePath":  "examples\\M3-2_Example_1 (DQN on Pong)\\M3-2_Example_1a (DQN on Pong, train).ipynb",
  "codePathLocal":  "M3-2_Example_1a (DQN on Pong, train).ipynb",
  "git":  {
    "remote":  "https://github.com/victorbrr17/Paradigms.git",
    "commit":  "b887677387057587a8f968af9219827d2644e609"
  },
  "email":  "victorbrr17@gmail.com",
  "root":  "c:\\Users\\victo\\OneDrive\\Escriptori\\3r\\Paradigms\\examples\\M3-2_Example_1 (DQN on Pong)",
  "host":  "Asus17",
  "executable":  "c:\\Users\\victo\\anaconda3\\envs\\gym_env1\\python.exe",
  "cpu_count":  10,
  "cpu_count_logical":  16,
  "gpu":  "NVIDIA GeForce RTX 3050 Laptop GPU",
  "gpu_count":  1,
  "disk":  {
    "/":  {
      "total":  "510683058176",
      "used":  "225420840960"
    }
  },
  "memory":  {
    "total":  "16782184448"
  },
  "gpu_nvidia":  [
    {
      "name":  "NVIDIA GeForce RTX 3050 Laptop GPU",
      "memoryTotal":  "4294967296",
      "cudaCores":  2048,
      "architecture":  "Ampere",
      "uuid":  "GPU-b41f6ac5-405f-0f45-c25b-8011bdf3a682"
    }
  ],
  "cudaVersion":  "12.7",
  "writerId":  "1u2dleaoyda4dksztif2od5yqd0hy7hx"
}